neuronmd/__init__.py
neuronmd/fitzhugh_nagumo.py
neuronmd/hhmodel.py
neuronmd/izhikevich.py
neuronmd-0.1.2.dist-info/LICENSE
neuronmd-0.1.2.dist-info/METADATA
neuronmd-0.1.2.dist-info/WHEEL
neuronmd-0.1.2.dist-info/top_level.txt
neuronmd-0.1.2.dist-info/RECORD
