Metadata-Version: 2.1
Name: neuronmd
Version: 0.1.2
Summary: Package for simulating spiking neuron models
Home-page: https://github.com/sowmyamanojna/neuronmd
Author: N Sowmya Manojna
Author-email: sowmyamanojna@gmail.com
License: MIT
Project-URL: Bug Tracker, https://github.com/sowmyamanojna/neuronmd/issues
Platform: UNKNOWN
License-File: LICENSE
Requires-Dist: numpy
Requires-Dist: scipy
Requires-Dist: tqdm
Requires-Dist: matplotlib
Requires-Dist: imageio
